drivecycle/__init__.py
drivecycle/energy.py
drivecycle/plots.py
drivecycle/route.py
drivecycle/simplification.py
drivecycle/trajectory.py
drivecycle-0.2.0.dist-info/METADATA
drivecycle-0.2.0.dist-info/WHEEL
drivecycle-0.2.0.dist-info/licenses/LICENSE
drivecycle-0.2.0.dist-info/RECORD
