Metadata-Version: 2.1
Name: drivecycle
Version: 0.2.0
Summary: Create drivecycles and energy consumption simulations for vehicles.
Project-URL: Homepage, https://saadiqm.com/drivecycle/
Author-email: Saadiq Mohiuddin <saadiq.mohiuddin@gmail.com>
License:                     GNU GENERAL PUBLIC LICENSE
License-File: LICENSE
Keywords: drivecycle
Classifier: Intended Audience :: Information Technology
Classifier: Intended Audience :: Science/Research
Classifier: Programming Language :: Python :: 3.8
Classifier: Programming Language :: Python :: 3.9
Classifier: Programming Language :: Python :: 3.10
Classifier: Programming Language :: Python :: 3.11
Classifier: Topic :: Scientific/Engineering :: GIS
Requires-Python: >=3.8
Requires-Dist: geopandas
Requires-Dist: numpy
Requires-Dist: scipy
Provides-Extra: dev
Requires-Dist: black; extra == 'dev'
Requires-Dist: flake8; extra == 'dev'
Requires-Dist: isort; extra == 'dev'
Requires-Dist: mypy; extra == 'dev'
Requires-Dist: pytest; extra == 'dev'
Requires-Dist: sphinx; extra == 'dev'
Provides-Extra: test
Requires-Dist: pytest; extra == 'test'
